data_suite/__init__.py
data_suite/version.py
data_suite/data/__init__.py
data_suite/data/data_loader.py
data_suite/models/__init__.py
data_suite/models/base_model.py
data_suite/models/benchmarks.py
data_suite/models/conformal.py
data_suite/models/copula.py
data_suite/models/ensemble.py
data_suite/models/mcd.py
data_suite/models/nn_conformal.py
data_suite/models/representation.py
data_suite/utils/__init__.py
data_suite/utils/data_utils.py
data_suite/utils/graphics.py
data_suite/utils/helpers.py
data_suite/utils/uncertainty_metrics.py
data_suite-0.2.1.dist-info/LICENSE
data_suite-0.2.1.dist-info/METADATA
data_suite-0.2.1.dist-info/WHEEL
data_suite-0.2.1.dist-info/top_level.txt
data_suite-0.2.1.dist-info/RECORD
