Metadata-Version: 2.2
Name: data_suite
Version: 0.2.1
Summary: Data-centric identification of in-distribution incongruous examples
Home-page: https://arxiv.org/abs/2202.08836
Author: Nabeel Seedat
Author-email: seedatnabeel@gmail.com
License: Apache 2.0
Keywords: data-centric AI,data quality,uncertainty
Platform: any
Classifier: License :: OSI Approved :: Apache Software License
Classifier: Development Status :: 4 - Beta
Classifier: Programming Language :: Python
Requires-Python: <3.10
License-File: LICENSE
Requires-Dist: copulas==0.6.0
Requires-Dist: nonconformist==2.1.0
Requires-Dist: numpy
Requires-Dist: pandas
Requires-Dist: opentsne
Requires-Dist: papermill
Requires-Dist: pyod==1.0.1
Requires-Dist: scikit-learn-extra
Requires-Dist: scikit_learn
Requires-Dist: scipy
Requires-Dist: suod
Requires-Dist: tensorflow
Requires-Dist: torch
Requires-Dist: torchvision
Requires-Dist: wandb
Requires-Dist: xlrd==2.0.1
Provides-Extra: benchmarks
Requires-Dist: aix360; extra == "benchmarks"
Requires-Dist: alibi-detect==0.9.1; extra == "benchmarks"
Requires-Dist: tensorflow>2; extra == "benchmarks"
Requires-Dist: uq360==0.2; extra == "benchmarks"
Provides-Extra: contribute
Requires-Dist: black; extra == "contribute"
Requires-Dist: flake8; extra == "contribute"
Requires-Dist: isort; extra == "contribute"
Requires-Dist: notebook; extra == "contribute"
Requires-Dist: pre-commit; extra == "contribute"
Provides-Extra: all
Requires-Dist: aix360; extra == "all"
Requires-Dist: alibi-detect==0.9.1; extra == "all"
Requires-Dist: tensorflow>2; extra == "all"
Requires-Dist: uq360==0.2; extra == "all"
Requires-Dist: black; extra == "all"
Requires-Dist: flake8; extra == "all"
Requires-Dist: isort; extra == "all"
Requires-Dist: notebook; extra == "all"
Requires-Dist: pre-commit; extra == "all"
